semio.py
semio-1.0.0.dist-info/entry_points.txt
semio-1.0.0.dist-info/LICENSE.md
semio-1.0.0.dist-info/METADATA
semio-1.0.0.dist-info/WHEEL
semio-1.0.0.dist-info/RECORD
